Metadata-Version: 2.1
Name: pkgsysoev
Version: 0.1.2
Summary: A example Python package
Home-page: https://github.com/Mr3zee
Author: Sysoev Alexander
Author-email: shudson@anl.gov
License: MIT
Platform: UNKNOWN
Classifier: Programming Language :: Python :: 3.9
License-File: LICENSE
